ditalini/README.md
ditalini/__init__.py
ditalini/ditalini.cpython-311-darwin.so
ditalini/ditalini_ext.cpp
ditalini/examples/example_square.py
include/doctest/doctest.h
include/doctest/extensions/doctest_mpi.h
include/doctest/extensions/doctest_util.h
include/doctest/extensions/mpi_reporter.h
include/doctest/extensions/mpi_sub_comm.h
lib/cmake/doctest/doctest.cmake
lib/cmake/doctest/doctestAddTests.cmake
lib/cmake/doctest/doctestConfig.cmake
lib/cmake/doctest/doctestConfigVersion.cmake
lib/cmake/doctest/doctestTargets.cmake
ditalini-0.1.0.dist-info/METADATA
ditalini-0.1.0.dist-info/WHEEL
ditalini-0.1.0.dist-info/licenses/LICENSE
ditalini-0.1.0.dist-info/RECORD
