Metadata-Version: 2.1
Name: ditalini
Version: 0.1.0
Requires-Python: >=3.8
Requires-Dist: numpy
